mkc/__init__.py
mkc/__main__.py
mkc/formulas.py
mkc/images.py
mkc/macros.py
usr/share/mkc/latex/main.tex
make_kindle_collection-1.5.9.dist-info/LICENCE
make_kindle_collection-1.5.9.dist-info/METADATA
make_kindle_collection-1.5.9.dist-info/WHEEL
make_kindle_collection-1.5.9.dist-info/entry_points.txt
make_kindle_collection-1.5.9.dist-info/top_level.txt
make_kindle_collection-1.5.9.dist-info/RECORD
