Metadata-Version: 2.1
Name: make-kindle-collection
Version: 1.5.9
Summary: Make Kindle collection
Home-page: https://gitlab.com/pacholik1/MKC
Author: Vojtěch Pachol
Author-email: pacholick@gmail.com
License: LGPL-3.0
Keywords: python,ebook,kindle
Platform: UNKNOWN
Classifier: Development Status :: 5 - Production/Stable
Classifier: Programming Language :: Python :: 3
Requires-Dist: Pillow
Requires-Dist: beautifulsoup4
Requires-Dist: brackettree
Requires-Dist: cairosvg
Requires-Dist: httplib2
